[
  {
    "backdrop_path": "Vridavan-1-5bd1f0e8c94a23d76e72b3f1a8c0d5ee",
    "id": "rF2EjoYhJmR",
    "overview": "",
    "poster_path": "",
    "release_date": "2026-01-22",
    "title": "Dharm Dharmantaran va Samvidhan",
    "video": "/Dharm-Dharmantaran-va-Sambidhan_-New-Mujic-For-Record(1080P_HD)-0c1c5518fef435f93e0047029106558f/master.m3u8",
    "vote_average": 9.8,
    "item_type": "podcast"
  },
  
  {
    "backdrop_path": "haridwar-9e41c7ab2f50836d1bce4a99f8d32755",
    "id": "rb06e697d76",
    "overview": "A sharp clash between political power and spiritual wisdom. This trailer uncovers hidden motives, rising tensions, and the battle between worldly ambition and true Brahmgyan. A thought-provoking glimpse into truth, manipulation, and awakening.",
    "poster_path": "Haridwar-thumbnail-084e9e27b61e58334533cf6c8d23193d",
    "release_date": "2025-11-17",
    "title": "Politics Politicians and Spiritual Wisdom",
    "video": "/Rajneta-Rajniti-v-Brahmgyan-Podcast(1080P_HD)-9de4e98b2af182b083366e598452439a/master.m3u8",
    "vote_average": 9.8,
    "item_type": "podcast"
  },
  {
    "backdrop_path": "sankhnad-1-thumbnail-f9812265-bbcd-4c20-afe6-e1f05ef23e41",
    "id": "rb06e6rhs3",
    "overview": "A sharp clash between political power and spiritual wisdom. This trailer uncovers hidden motives, rising tensions, and the battle between worldly ambition and true Brahmgyan. A thought-provoking glimpse into truth, manipulation, and awakening.",
    "poster_path": "sankhnad-1-thumbnail-f9812265-bbcd-4c20-afe6-e1f05ef23e41",
    "release_date": "2025-11-17",
    "title": "Sankhnad Episode 1 - Kis sajish ke sikar Sant Shri Asharamji Bapu",
    "video": "/kIs-Sajis-ke-Sikar-Sant-Asharam-Bapu(1080P_HD)_b29a02fb28f726018966c1e196967514-fc28a3e69905e805962e9bd785263c85/master.m3u8",
    "vote_average": 9.8,
    "item_type": "podcast"
  }
  
]